nevora/__init__.py
nevora/converter.py
nevora/utils.py
nevora-0.1.0.dist-info/licenses/LICENSE
nevora-0.1.0.dist-info/METADATA
nevora-0.1.0.dist-info/WHEEL
nevora-0.1.0.dist-info/top_level.txt
nevora-0.1.0.dist-info/RECORD
